{
 "api": [
  {
   "attKind": "standard",
   "attReports": {
    "0": ""
   },
   "body": "self._Text = pixcCommon.execAttribute(\"\", self._Text, val, doSet)\r\nreturn self._Text\r\n",
   "kind": "func",
   "name": "Text",
   "params": [
    {
     "name": "val",
     "type": "string"
    },
    {
     "name": "doSet",
     "type": "bool"
    }
   ],
   "result": {
    "name": "result",
    "type": "string"
   },
   "slotStyle": "leftIn;rightNone;triggerHidden"
  },
  {
   "body": "local text = self.Text(nil, false)\r\npixc.callRefs(text)\r\nreturn text\r\n",
   "kind": "func",
   "name": "sendText",
   "slotStyle": "leftIn;rightOut"
  },
  {
   "body": "self.Text('', true)\r\n",
   "kind": "func",
   "name": "reset",
   "slotStyle": "rightNone"
  }
 ],
 "definedExternally": false,
 "hostInfo": {
  "systemType": ""
 },
 "license": "1GNTlyr7sewU1l3S6nhV4gwKOetR2oUehkwzRBb2aWCrb4fUZaH7uqMPRp9ogxixo2+72tjTfl009Xa6ENoIf38XRgL1kLji+0C2zrUafHYmkWdODB0qkdlhm77ecbhXk6h+TG90b4jE9LMmZURvcw==",
 "name": "SendText",
 "properties": [
  {
   "cont": "false",
   "name": "Auto Init",
   "typeHint": "bool"
  },
  {
   "cont": "AV Stumpfl GmbH (CF)",
   "name": "Author",
   "readOnly": true,
   "typeHint": "string"
  },
  {
   "cont": "1",
   "name": "Version",
   "readOnly": true,
   "typeHint": "number"
  },
  {
   "cont": "Forwards (sends) a text on a call of sendText. The text can be reset by calling reset.  This action can be used to avoid sending every single character to an output.",
   "name": "Description",
   "readOnly": true,
   "typeHint": "string"
  }
 ],
 "separateCode": false,
 "uiUrl": ""
}